change_detection/__init__.py
change_detection/change_detection.R
change_detection/functions.py
change_detection/results_extract.R
change_detection/trend_isat_functions.R
change_detection-0.3.5.dist-info/WHEEL
change_detection-0.3.5.dist-info/METADATA
change_detection-0.3.5.dist-info/RECORD
