Metadata-Version: 2.1
Name: change_detection
Version: 0.3.5
Summary: package for detecting change in time-series data
Home-page: https://github.com/ebmdatalab/change_detection
License: UNKNOWN
Author: Alex Walker
Author-email: alex.walker@phc.ox.ac.uk
Classifier: License :: OSI Approved :: MIT License
Requires-Dist: pandas >= 0.24
Requires-Dist: pandas-gbq >= 0.8.0
Requires-Dist: numpy
Requires-Dist: rpy2
Requires-Dist: ebmdatalab >=0.0.20
